{"month": "Aashadha", "data": [{"enDate": "2019-6-16", "npDate": "2076-3-1", "event": {"title": "--", "npDay": "\u0967", "enDay": "16", "holiday": "false"}, "tithi": "\u091a\u0924\u0941\u0930\u094d\u0926\u0936\u0940"}, {"enDate": "2019-6-17", "npDate": "2076-3-2", "event": {"title": "\u091c\u094d\u092f\u093e: \u092a\u0941\u0928\u094d\u0939\u093f/\u092a\u0928\u094c\u0924\u0940 \u0938\u094d\u0928\u093e\u0928/\u0935\u093f\u0936\u094d\u0935 \u0916\u0921\u0947\u0930\u0940 \u0935\u093f\u0930\u0941\u0926\u094d\u0927 \u0938\u0902\u0918\u0930\u094d\u0937 \u0926\u093f\u0935\u0938", "npDay": "\u0968", "enDay": "17", "holiday": "false"}, "tithi": "\u092a\u0942\u0930\u094d\u0923\u093f\u092e\u093e"}, {"enDate": "2019-6-18", "npDate": "2076-3-3", "event": {"title": "--", "npDay": "\u0969", "enDay": "18", "holiday": "false"}, "tithi": "\u092a\u094d\u0930\u0924\u093f\u092a\u0926\u093e"}, {"enDate": "2019-6-19", "npDate": "2076-3-4", "event": {"title": "--", "npDay": "\u096a", "enDay": "19", "holiday": "false"}, "tithi": "\u0926\u094d\u0935\u093f\u0924\u0940\u092f\u093e"}, {"enDate": "2019-6-20", "npDate": "2076-3-5", "event": {"title": "--", "npDay": "\u096b", "enDay": "20", "holiday": "false"}, "tithi": "\u0924\u0943\u0924\u093f\u092f\u093e"}, {"enDate": "2019-6-21", "npDate": "2076-3-6", "event": {"title": "\u0938\u092c\u0948\u092d\u0928\u094d\u0926\u093e \u0932\u093e\u092e\u094b \u0926\u093f\u0928", "npDay": "\u096c", "enDay": "21", "holiday": "false"}, "tithi": "\u091a\u0924\u0941\u0930\u094d\u0925\u0940"}, {"enDate": "2019-6-22", "npDate": "2076-3-7", "event": {"title": "--", "npDay": "\u096d", "enDay": "22", "holiday": "false"}, "tithi": "\u092a\u091e\u094d\u091a\u092e\u0940"}, {"enDate": "2019-6-23", "npDate": "2076-3-8", "event": {"title": "\u0905\u0928\u094d\u0924\u0930\u093e\u0937\u094d\u091f\u094d\u0930\u093f\u092f \u090f\u0915\u0932 \u092e\u0939\u093f\u0932\u093e \u0926\u093f\u0935\u0938", "npDay": "\u096e", "enDay": "23", "holiday": "false"}, "tithi": "\u0937\u0937\u094d\u0920\u0940"}, {"enDate": "2019-6-24", "npDate": "2076-3-9", "event": {"title": "--", "npDay": "\u096f", "enDay": "24", "holiday": "false"}, "tithi": "\u0938\u092a\u094d\u0924\u092e\u0940"}, {"enDate": "2019-6-25", "npDate": "2076-3-10", "event": {"title": "--", "npDay": "\u0967\u0966", "enDay": "25", "holiday": "false"}, "tithi": "\u0905\u0937\u094d\u091f\u092e\u0940"}, {"enDate": "2019-6-26", "npDate": "2076-3-11", "event": {"title": "--", "npDay": "\u0967\u0967", "enDay": "26", "holiday": "false"}, "tithi": "\u0928\u0935\u092e\u0940"}, {"enDate": "2019-6-27", "npDate": "2076-3-12", "event": {"title": "--", "npDay": "\u0967\u0968", "enDay": "27", "holiday": "false"}, "tithi": "\u0926\u0936\u092e\u0940"}, {"enDate": "2019-6-28", "npDate": "2076-3-13", "event": {"title": "\u092f\u094b\u0917\u093f\u0928\u0940 \u090f\u0915\u093e\u0926\u0936\u0940 \u0935\u094d\u0930\u0924", "npDay": "\u0967\u0969", "enDay": "28", "holiday": "false"}, "tithi": "\u090f\u0915\u093e\u0926\u0936\u0940"}, {"enDate": "2019-6-29", "npDate": "2076-3-14", "event": {"title": "\u0928\u0947\u092a\u093e\u0932 \u0917\u094c\u0930\u0935 \u092f\u093e\u0924\u094d\u0930\u093e", "npDay": "\u0967\u096a", "enDay": "29", "holiday": "false"}, "tithi": "\u0926\u094d\u0935\u093e\u0926\u0936\u0940"}, {"enDate": "2019-6-30", "npDate": "2076-3-15", "event": {"title": "--", "npDay": "\u0967\u096b", "enDay": "30", "holiday": "false"}, "tithi": "\u0924\u094d\u0930\u092f\u094b\u0926\u0936\u0940"}, {"enDate": "2019-7-1", "npDate": "2076-3-16", "event": {"title": "--", "npDay": "\u0967\u096c", "enDay": "1", "holiday": "false"}, "tithi": "\u091a\u0924\u0941\u0930\u094d\u0926\u0936\u0940"}, {"enDate": "2019-7-2", "npDate": "2076-3-17", "event": {"title": "--", "npDay": "\u0967\u096d", "enDay": "2", "holiday": "false"}, "tithi": "\u0914\u0902\u0938\u0940"}, {"enDate": "2019-7-3", "npDate": "2076-3-18", "event": {"title": "--", "npDay": "\u0967\u096e", "enDay": "3", "holiday": "false"}, "tithi": "\u092a\u094d\u0930\u0924\u093f\u092a\u0926\u093e"}, {"enDate": "2019-7-4", "npDate": "2076-3-19", "event": {"title": "--", "npDay": "\u0967\u096f", "enDay": "4", "holiday": "false"}, "tithi": "\u0926\u094d\u0935\u093f\u0924\u0940\u092f\u093e"}, {"enDate": "2019-7-5", "npDate": "2076-3-20", "event": {"title": "--", "npDay": "\u0968\u0966", "enDay": "5", "holiday": "false"}, "tithi": "\u0924\u0943\u0924\u093f\u092f\u093e"}, {"enDate": "2019-7-6", "npDate": "2076-3-21", "event": {"title": "--", "npDay": "\u0968\u0967", "enDay": "6", "holiday": "false"}, "tithi": "\u091a\u0924\u0941\u0930\u094d\u0925\u0940"}, {"enDate": "2019-7-7", "npDate": "2076-3-22", "event": {"title": "--", "npDay": "\u0968\u0968", "enDay": "7", "holiday": "false"}, "tithi": "\u092a\u091e\u094d\u091a\u092e\u0940"}, {"enDate": "2019-7-8", "npDate": "2076-3-23", "event": {"title": "--", "npDay": "\u0968\u0969", "enDay": "8", "holiday": "false"}, "tithi": "\u0937\u0937\u094d\u0920\u0940"}, {"enDate": "2019-7-9", "npDate": "2076-3-24", "event": {"title": "--", "npDay": "\u0968\u096a", "enDay": "9", "holiday": "false"}, "tithi": "\u0905\u0937\u094d\u091f\u092e\u0940"}, {"enDate": "2019-7-10", "npDate": "2076-3-25", "event": {"title": "--", "npDay": "\u0968\u096b", "enDay": "10", "holiday": "false"}, "tithi": "\u0905\u0937\u094d\u091f\u092e\u0940"}, {"enDate": "2019-7-11", "npDate": "2076-3-26", "event": {"title": "--", "npDay": "\u0968\u096c", "enDay": "11", "holiday": "false"}, "tithi": "\u0926\u0936\u092e\u0940"}, {"enDate": "2019-7-12", "npDate": "2076-3-27", "event": {"title": "\u0939\u0930\u093f\u0936\u092f\u0928\u0940 \u090f\u0915\u093e\u0926\u0936\u0940 \u0935\u094d\u0930\u0924/\u091a\u0924\u0941\u0930\u094d\u092e\u093e\u0938 \u0935\u094d\u0930\u0924 \u0906\u0930\u092e\u094d\u092d", "npDay": "\u0968\u096d", "enDay": "12", "holiday": "false"}, "tithi": "\u090f\u0915\u093e\u0926\u0936\u0940"}, {"enDate": "2019-7-13", "npDate": "2076-3-28", "event": {"title": "--", "npDay": "\u0968\u096e", "enDay": "13", "holiday": "false"}, "tithi": "\u0926\u094d\u0935\u093e\u0926\u0936\u0940"}, {"enDate": "2019-7-14", "npDate": "2076-3-29", "event": {"title": "--", "npDay": "\u0968\u096f", "enDay": "14", "holiday": "false"}, "tithi": "\u0924\u094d\u0930\u092f\u094b\u0926\u0936\u0940"}, {"enDate": "2019-7-15", "npDate": "2076-3-30", "event": {"title": "--", "npDay": "\u0969\u0966", "enDay": "15", "holiday": "false"}, "tithi": "\u091a\u0924\u0941\u0930\u094d\u0926\u0936\u0940"}, {"enDate": "2019-7-16", "npDate": "2076-3-31", "event": {"title": "\u0917\u0941\u0930\u0941 \u092a\u0941\u0930\u094d\u0923\u093f\u092e\u093e \u0935\u094d\u0930\u0924/\u0916\u0923\u094d\u0921\u0917\u094d\u0930\u093e\u0938 \u091a\u0928\u094d\u0926\u094d\u0930 \u0917\u094d\u0930\u0939\u0923", "npDay": "\u0969\u0967", "enDay": "16", "holiday": "false"}, "tithi": "\u092a\u0942\u0930\u094d\u0923\u093f\u092e\u093e"}]}